<?xml version="1.0" encoding="UTF-8"?>
<record_update table="sys_metadata_link">
    <sys_metadata_link action="INSERT_OR_UPDATE">
        <directory>unload.demo</directory>
        <documentkey>01074360db280b00d13efa9ebf9619eb</documentkey>
        <payload><![CDATA[<?xml version="1.0" encoding="UTF-8"?>
<record_update>
    <sys_choice action="INSERT_OR_UPDATE" field="state" table="sa_network_paths" version="3">
        <sys_choice action="INSERT_OR_UPDATE">
            <dependent_value/>
            <element>state</element>
            <hint/>
            <inactive>false</inactive>
            <label>検出待ち</label>
            <language>ja</language>
            <name>sa_network_paths</name>
            <sequence>1</sequence>
            <sys_created_by>system</sys_created_by>
            <sys_created_on>2017-08-10 02:31:43</sys_created_on>
            <sys_domain>global</sys_domain>
            <sys_domain_path>/</sys_domain_path>
            <sys_id>45074360db280b00d13efa9ebf9619ea</sys_id>
            <sys_mod_count>0</sys_mod_count>
            <sys_updated_by>system</sys_updated_by>
            <sys_updated_on>2017-08-10 02:31:43</sys_updated_on>
            <value>0</value>
        </sys_choice>
        <sys_choice action="INSERT_OR_UPDATE">
            <dependent_value/>
            <element>state</element>
            <hint/>
            <inactive>false</inactive>
            <label>等待 Discovery</label>
            <language>zh</language>
            <name>sa_network_paths</name>
            <sequence>1</sequence>
            <sys_created_by>Bruce.xu</sys_created_by>
            <sys_created_on>2017-08-10 03:36:13</sys_created_on>
            <sys_domain>global</sys_domain>
            <sys_domain_path>/</sys_domain_path>
            <sys_id>06c513e40f2cc3008e6805ace1050ead</sys_id>
            <sys_mod_count>0</sys_mod_count>
            <sys_updated_by>Bruce.xu</sys_updated_by>
            <sys_updated_on>2017-08-10 03:36:13</sys_updated_on>
            <value>0</value>
        </sys_choice>
        <sys_choice action="INSERT_OR_UPDATE">
            <dependent_value/>
            <element>state</element>
            <hint/>
            <inactive>false</inactive>
            <label>実行中</label>
            <language>ja</language>
            <name>sa_network_paths</name>
            <sequence>2</sequence>
            <sys_created_by>system</sys_created_by>
            <sys_created_on>2017-08-10 02:31:43</sys_created_on>
            <sys_domain>global</sys_domain>
            <sys_domain_path>/</sys_domain_path>
            <sys_id>49074360db280b00d13efa9ebf9619eb</sys_id>
            <sys_mod_count>0</sys_mod_count>
            <sys_updated_by>system</sys_updated_by>
            <sys_updated_on>2017-08-10 02:31:43</sys_updated_on>
            <value>1</value>
        </sys_choice>
        <sys_choice action="INSERT_OR_UPDATE">
            <dependent_value/>
            <element>state</element>
            <hint/>
            <inactive>false</inactive>
            <label>正在运行</label>
            <language>zh</language>
            <name>sa_network_paths</name>
            <sequence>2</sequence>
            <sys_created_by>Bruce.xu</sys_created_by>
            <sys_created_on>2017-08-10 03:36:13</sys_created_on>
            <sys_domain>global</sys_domain>
            <sys_domain_path>/</sys_domain_path>
            <sys_id>4ec513e40f2cc3008e6805ace1050ead</sys_id>
            <sys_mod_count>0</sys_mod_count>
            <sys_updated_by>Bruce.xu</sys_updated_by>
            <sys_updated_on>2017-08-10 03:36:13</sys_updated_on>
            <value>1</value>
        </sys_choice>
        <sys_choice action="INSERT_OR_UPDATE">
            <dependent_value/>
            <element>state</element>
            <hint/>
            <inactive>false</inactive>
            <label>完了</label>
            <language>ja</language>
            <name>sa_network_paths</name>
            <sequence>3</sequence>
            <sys_created_by>system</sys_created_by>
            <sys_created_on>2017-08-10 02:31:43</sys_created_on>
            <sys_domain>global</sys_domain>
            <sys_domain_path>/</sys_domain_path>
            <sys_id>01074360db280b00d13efa9ebf9619eb</sys_id>
            <sys_mod_count>0</sys_mod_count>
            <sys_updated_by>system</sys_updated_by>
            <sys_updated_on>2017-08-10 02:31:43</sys_updated_on>
            <value>2</value>
        </sys_choice>
        <sys_choice action="INSERT_OR_UPDATE">
            <dependent_value/>
            <element>state</element>
            <hint/>
            <inactive>false</inactive>
            <label>完成时间</label>
            <language>zh</language>
            <name>sa_network_paths</name>
            <sequence>3</sequence>
            <sys_created_by>Bruce.xu</sys_created_by>
            <sys_created_on>2017-08-10 03:36:13</sys_created_on>
            <sys_domain>global</sys_domain>
            <sys_domain_path>/</sys_domain_path>
            <sys_id>cac513e40f2cc3008e6805ace1050eac</sys_id>
            <sys_mod_count>1</sys_mod_count>
            <sys_updated_by>Bruce.xu</sys_updated_by>
            <sys_updated_on>2017-08-10 03:37:10</sys_updated_on>
            <value>2</value>
        </sys_choice>
        <sys_choice_set action="INSERT_OR_UPDATE">
            <element>state</element>
            <name>sa_network_paths</name>
            <sys_class_name>sys_choice_set</sys_class_name>
            <sys_created_by>system</sys_created_by>
            <sys_created_on>2017-08-10 02:31:43</sys_created_on>
            <sys_id>c9074360db280b00d13efa9ebf9619ea</sys_id>
            <sys_mod_count>0</sys_mod_count>
            <sys_name>state</sys_name>
            <sys_package display_value="I18N: Japanese Translations" source="com.snc.i18n.japanese">d32507a4dbe40b00d13efa9ebf9619d5</sys_package>
            <sys_policy/>
            <sys_scope display_value="Global">global</sys_scope>
            <sys_update_name>sys_choice_sa_network_paths_state</sys_update_name>
            <sys_updated_by>system</sys_updated_by>
            <sys_updated_on>2017-08-10 02:31:43</sys_updated_on>
        </sys_choice_set>
    </sys_choice>
</record_update>
]]></payload>
        <sys_class_name>sys_metadata_link</sys_class_name>
        <sys_created_by>Fayu.xu</sys_created_by>
        <sys_created_on>2018-03-07 04:05:14</sys_created_on>
        <sys_id>34b0bf7f0f20d7005969b57ce1050e16</sys_id>
        <sys_mod_count>0</sys_mod_count>
        <sys_name>完了</sys_name>
        <sys_package display_value="HACN" source="x_sogd_hacn">7f3b2e0adb260740d13efa9ebf9619da</sys_package>
        <sys_policy/>
        <sys_scope display_value="HACN">7f3b2e0adb260740d13efa9ebf9619da</sys_scope>
        <sys_update_name>sys_metadata_link_34b0bf7f0f20d7005969b57ce1050e16</sys_update_name>
        <sys_updated_by>Fayu.xu</sys_updated_by>
        <sys_updated_on>2018-03-07 04:05:14</sys_updated_on>
        <tablename>sys_choice</tablename>
    </sys_metadata_link>
</record_update>
