<?xml version="1.0" encoding="UTF-8"?>
<record_update table="sys_metadata_link">
    <sys_metadata_link action="INSERT_OR_UPDATE">
        <directory>unload.demo</directory>
        <documentkey>00651fe00f2cc3008e6805ace1050ebe</documentkey>
        <payload><![CDATA[<?xml version="1.0" encoding="UTF-8"?>
<record_update>
    <sys_choice action="INSERT_OR_UPDATE" field="state" table="discovery_status" version="3">
        <sys_choice action="INSERT_OR_UPDATE">
            <dependent_value/>
            <element>state</element>
            <hint/>
            <inactive>false</inactive>
            <label>Starting</label>
            <language>en</language>
            <name>discovery_status</name>
            <sequence>0</sequence>
            <sys_created_by>system</sys_created_by>
            <sys_created_on>2017-07-28 11:25:16</sys_created_on>
            <sys_domain>global</sys_domain>
            <sys_domain_path>/</sys_domain_path>
            <sys_id>de740228db500300d13efa9ebf961982</sys_id>
            <sys_mod_count>0</sys_mod_count>
            <sys_updated_by>system</sys_updated_by>
            <sys_updated_on>2017-07-28 11:25:16</sys_updated_on>
            <value>Starting</value>
        </sys_choice>
        <sys_choice action="INSERT_OR_UPDATE">
            <dependent_value/>
            <element>state</element>
            <hint/>
            <inactive>false</inactive>
            <label>正在启动</label>
            <language>zh</language>
            <name>discovery_status</name>
            <sequence>0</sequence>
            <sys_created_by>Bruce.xu</sys_created_by>
            <sys_created_on>2017-08-10 03:34:27</sys_created_on>
            <sys_domain>global</sys_domain>
            <sys_domain_path>/</sys_domain_path>
            <sys_id>c8651fe00f2cc3008e6805ace1050ebe</sys_id>
            <sys_mod_count>0</sys_mod_count>
            <sys_updated_by>Bruce.xu</sys_updated_by>
            <sys_updated_on>2017-08-10 03:34:27</sys_updated_on>
            <value>Starting</value>
        </sys_choice>
        <sys_choice action="INSERT_OR_UPDATE">
            <dependent_value/>
            <element>state</element>
            <hint/>
            <inactive>false</inactive>
            <label>開始中</label>
            <language>ja</language>
            <name>discovery_status</name>
            <sequence>0</sequence>
            <sys_created_by>system</sys_created_by>
            <sys_created_on>2017-08-10 02:31:21</sys_created_on>
            <sys_domain>global</sys_domain>
            <sys_domain_path>/</sys_domain_path>
            <sys_id>b3e60b20db280b00d13efa9ebf961978</sys_id>
            <sys_mod_count>0</sys_mod_count>
            <sys_updated_by>system</sys_updated_by>
            <sys_updated_on>2017-08-10 02:31:21</sys_updated_on>
            <value>Starting</value>
        </sys_choice>
        <sys_choice action="INSERT_OR_UPDATE">
            <dependent_value/>
            <element>state</element>
            <hint/>
            <inactive>false</inactive>
            <label>Active</label>
            <language>en</language>
            <name>discovery_status</name>
            <sequence>1</sequence>
            <sys_created_by>system</sys_created_by>
            <sys_created_on>2017-07-28 11:25:16</sys_created_on>
            <sys_domain>global</sys_domain>
            <sys_domain_path>/</sys_domain_path>
            <sys_id>12740228db500300d13efa9ebf961983</sys_id>
            <sys_mod_count>0</sys_mod_count>
            <sys_updated_by>system</sys_updated_by>
            <sys_updated_on>2017-07-28 11:25:16</sys_updated_on>
            <value>Active</value>
        </sys_choice>
        <sys_choice action="INSERT_OR_UPDATE">
            <dependent_value/>
            <element>state</element>
            <hint/>
            <inactive>false</inactive>
            <label>アクティブ</label>
            <language>ja</language>
            <name>discovery_status</name>
            <sequence>1</sequence>
            <sys_created_by>system</sys_created_by>
            <sys_created_on>2017-08-10 02:31:21</sys_created_on>
            <sys_domain>global</sys_domain>
            <sys_domain_path>/</sys_domain_path>
            <sys_id>3fe60b20db280b00d13efa9ebf961976</sys_id>
            <sys_mod_count>0</sys_mod_count>
            <sys_updated_by>system</sys_updated_by>
            <sys_updated_on>2017-08-10 02:31:21</sys_updated_on>
            <value>Active</value>
        </sys_choice>
        <sys_choice action="INSERT_OR_UPDATE">
            <dependent_value/>
            <element>state</element>
            <hint/>
            <inactive>false</inactive>
            <label>活动</label>
            <language>zh</language>
            <name>discovery_status</name>
            <sequence>1</sequence>
            <sys_created_by>Bruce.xu</sys_created_by>
            <sys_created_on>2017-08-10 03:34:27</sys_created_on>
            <sys_domain>global</sys_domain>
            <sys_domain_path>/</sys_domain_path>
            <sys_id>44651fe00f2cc3008e6805ace1050ebd</sys_id>
            <sys_mod_count>0</sys_mod_count>
            <sys_updated_by>Bruce.xu</sys_updated_by>
            <sys_updated_on>2017-08-10 03:34:27</sys_updated_on>
            <value>Active</value>
        </sys_choice>
        <sys_choice action="INSERT_OR_UPDATE">
            <dependent_value/>
            <element>state</element>
            <hint/>
            <inactive>false</inactive>
            <label>Completed</label>
            <language>en</language>
            <name>discovery_status</name>
            <sequence>2</sequence>
            <sys_created_by>system</sys_created_by>
            <sys_created_on>2017-07-28 11:25:16</sys_created_on>
            <sys_domain>global</sys_domain>
            <sys_domain_path>/</sys_domain_path>
            <sys_id>52740228db500300d13efa9ebf961983</sys_id>
            <sys_mod_count>0</sys_mod_count>
            <sys_updated_by>system</sys_updated_by>
            <sys_updated_on>2017-07-28 11:25:16</sys_updated_on>
            <value>Completed</value>
        </sys_choice>
        <sys_choice action="INSERT_OR_UPDATE">
            <dependent_value/>
            <element>state</element>
            <hint/>
            <inactive>false</inactive>
            <label>完了</label>
            <language>ja</language>
            <name>discovery_status</name>
            <sequence>2</sequence>
            <sys_created_by>system</sys_created_by>
            <sys_created_on>2017-08-10 02:31:21</sys_created_on>
            <sys_domain>global</sys_domain>
            <sys_domain_path>/</sys_domain_path>
            <sys_id>73e60b20db280b00d13efa9ebf961976</sys_id>
            <sys_mod_count>0</sys_mod_count>
            <sys_updated_by>system</sys_updated_by>
            <sys_updated_on>2017-08-10 02:31:21</sys_updated_on>
            <value>Completed</value>
        </sys_choice>
        <sys_choice action="INSERT_OR_UPDATE">
            <dependent_value/>
            <element>state</element>
            <hint/>
            <inactive>false</inactive>
            <label>已完成</label>
            <language>zh</language>
            <name>discovery_status</name>
            <sequence>2</sequence>
            <sys_created_by>Bruce.xu</sys_created_by>
            <sys_created_on>2017-08-10 03:34:27</sys_created_on>
            <sys_domain>global</sys_domain>
            <sys_domain_path>/</sys_domain_path>
            <sys_id>84651fe00f2cc3008e6805ace1050ebf</sys_id>
            <sys_mod_count>0</sys_mod_count>
            <sys_updated_by>Bruce.xu</sys_updated_by>
            <sys_updated_on>2017-08-10 03:34:27</sys_updated_on>
            <value>Completed</value>
        </sys_choice>
        <sys_choice action="INSERT_OR_UPDATE">
            <dependent_value/>
            <element>state</element>
            <hint/>
            <inactive>false</inactive>
            <label>Canceled</label>
            <language>en</language>
            <name>discovery_status</name>
            <sequence>3</sequence>
            <sys_created_by>system</sys_created_by>
            <sys_created_on>2017-07-28 11:25:16</sys_created_on>
            <sys_domain>global</sys_domain>
            <sys_domain_path>/</sys_domain_path>
            <sys_id>92740228db500300d13efa9ebf961983</sys_id>
            <sys_mod_count>0</sys_mod_count>
            <sys_updated_by>system</sys_updated_by>
            <sys_updated_on>2017-07-28 11:25:16</sys_updated_on>
            <value>Canceled</value>
        </sys_choice>
        <sys_choice action="INSERT_OR_UPDATE">
            <dependent_value/>
            <element>state</element>
            <hint/>
            <inactive>false</inactive>
            <label>キャンセル</label>
            <language>ja</language>
            <name>discovery_status</name>
            <sequence>3</sequence>
            <sys_created_by>system</sys_created_by>
            <sys_created_on>2017-08-10 02:31:21</sys_created_on>
            <sys_domain>global</sys_domain>
            <sys_domain_path>/</sys_domain_path>
            <sys_id>f7e60b20db280b00d13efa9ebf961977</sys_id>
            <sys_mod_count>0</sys_mod_count>
            <sys_updated_by>system</sys_updated_by>
            <sys_updated_on>2017-08-10 02:31:21</sys_updated_on>
            <value>Canceled</value>
        </sys_choice>
        <sys_choice action="INSERT_OR_UPDATE">
            <dependent_value/>
            <element>state</element>
            <hint/>
            <inactive>false</inactive>
            <label>已取消</label>
            <language>zh</language>
            <name>discovery_status</name>
            <sequence>3</sequence>
            <sys_created_by>Bruce.xu</sys_created_by>
            <sys_created_on>2017-08-10 03:34:27</sys_created_on>
            <sys_domain>global</sys_domain>
            <sys_domain_path>/</sys_domain_path>
            <sys_id>00651fe00f2cc3008e6805ace1050ebe</sys_id>
            <sys_mod_count>0</sys_mod_count>
            <sys_updated_by>Bruce.xu</sys_updated_by>
            <sys_updated_on>2017-08-10 03:34:27</sys_updated_on>
            <value>Canceled</value>
        </sys_choice>
        <sys_choice_set action="INSERT_OR_UPDATE">
            <element>state</element>
            <name>discovery_status</name>
            <sys_class_name>sys_choice_set</sys_class_name>
            <sys_created_by>system</sys_created_by>
            <sys_created_on>2017-07-28 11:25:16</sys_created_on>
            <sys_id>96740228db500300d13efa9ebf961983</sys_id>
            <sys_mod_count>0</sys_mod_count>
            <sys_name>state</sys_name>
            <sys_package display_value="Core Automation" source="com.snc.core.automation">f4644ae4db500300d13efa9ebf961965</sys_package>
            <sys_policy/>
            <sys_scope display_value="Global">global</sys_scope>
            <sys_update_name>sys_choice_discovery_status_state</sys_update_name>
            <sys_updated_by>system</sys_updated_by>
            <sys_updated_on>2017-07-28 11:25:16</sys_updated_on>
        </sys_choice_set>
    </sys_choice>
</record_update>
]]></payload>
        <sys_class_name>sys_metadata_link</sys_class_name>
        <sys_created_by>Fayu.xu</sys_created_by>
        <sys_created_on>2018-03-07 04:03:01</sys_created_on>
        <sys_id>1830b77f0f20d7005969b57ce1050ebd</sys_id>
        <sys_mod_count>0</sys_mod_count>
        <sys_name>已取消</sys_name>
        <sys_package display_value="HACN" source="x_sogd_hacn">7f3b2e0adb260740d13efa9ebf9619da</sys_package>
        <sys_policy/>
        <sys_scope display_value="HACN">7f3b2e0adb260740d13efa9ebf9619da</sys_scope>
        <sys_update_name>sys_metadata_link_1830b77f0f20d7005969b57ce1050ebd</sys_update_name>
        <sys_updated_by>Fayu.xu</sys_updated_by>
        <sys_updated_on>2018-03-07 04:03:01</sys_updated_on>
        <tablename>sys_choice</tablename>
    </sys_metadata_link>
</record_update>
